godaddy_reseller_client/__init__.py
godaddy_reseller_client/certificates.py
godaddy_reseller_client/countries.py
godaddy_reseller_client/domains.py
godaddy_reseller_client/schema.py
godaddy_reseller_client/shoppers.py
godaddy_reseller_client-0.9.2.dist-info/LICENCE
godaddy_reseller_client-0.9.2.dist-info/METADATA
godaddy_reseller_client-0.9.2.dist-info/WHEEL
godaddy_reseller_client-0.9.2.dist-info/top_level.txt
godaddy_reseller_client-0.9.2.dist-info/RECORD
