Metadata-Version: 2.1
Name: godaddy-reseller-client
Version: 0.9.2
Summary: A small wrapper client of godaddy reseller api
Home-page: https://github.com/bychis/godaddy-reseller
Author: Bokhari Chemseddine Ismail
Author-email: bychis6@gmail.com
License: UNKNOWN
Project-URL: Bug Tracker, https://github.com/bychis/godaddy-reseller/issues
Platform: UNKNOWN
Classifier: Programming Language :: Python :: 3
Classifier: License :: OSI Approved :: MIT License
Classifier: Operating System :: OS Independent
Requires-Python: >=3.6
License-File: LICENCE
